{"chars": [{"ignore": 0, "transcription": "\u805a", "points": [407, 106, 465, 106, 465, 158, 407, 158]}, {"ignore": 0, "transcription": "\u767e", "points": [408, 177, 463, 177, 463, 223, 408, 223]}, {"ignore": 0, "transcription": "\u8766", "points": [548, 94, 729, 94, 729, 255, 548, 255]}, {"ignore": 0, "transcription": "\u5175", "points": [793, 92, 966, 92, 966, 252, 793, 252]}, {"ignore": 0, "transcription": "\u87f9", "points": [1027, 93, 1197, 93, 1197, 247, 1027, 247]}, {"ignore": 0, "transcription": "\u7172", "points": [1258, 92, 1434, 92, 1434, 245, 1258, 245]}, {"ignore": 0, "transcription": "\u8fd9", "points": [183, 264, 226, 264, 226, 302, 183, 302]}, {"ignore": 0, "transcription": "\u662f", "points": [235, 260, 275, 260, 275, 304, 235, 304]}, {"ignore": 0, "transcription": "\u53ef", "points": [283, 264, 323, 264, 323, 302, 283, 302]}, {"ignore": 0, "transcription": "\u4ee5", "points": [327, 267, 373, 267, 373, 302, 327, 302]}, {"ignore": 0, "transcription": "\u5148", "points": [373, 261, 416, 261, 416, 304, 373, 304]}, {"ignore": 0, "transcription": "\u5403", "points": [420, 266, 467, 266, 467, 299, 420, 299]}, {"ignore": 0, "transcription": "\u540e", "points": [218, 317, 255, 317, 255, 356, 218, 356]}, {"ignore": 0, "transcription": "\u6dae", "points": [259, 312, 308, 312, 308, 353, 259, 353]}, {"ignore": 0, "transcription": "\u7684", "points": [310, 314, 353, 314, 353, 352, 310, 352]}, {"ignore": 0, "transcription": "\u5e72", "points": [357, 316, 398, 316, 398, 352, 357, 352]}, {"ignore": 0, "transcription": "\u9505", "points": [403, 312, 449, 312, 449, 354, 403, 354]}, {"ignore": 0, "transcription": "\u83dc", "points": [455, 311, 492, 311, 492, 356, 455, 356]}, {"ignore": 0, "transcription": "\u52a0", "points": [549, 294, 610, 294, 610, 349, 549, 349]}, {"ignore": 0, "transcription": "\u76df", "points": [605, 293, 668, 293, 668, 349, 605, 349]}, {"ignore": 0, "transcription": "\u7535", "points": [670, 293, 722, 293, 722, 346, 670, 346]}, {"ignore": 0, "transcription": "\u8bdd", "points": [722, 293, 783, 293, 783, 347, 722, 347]}, {"ignore": 0, "transcription": "\uff1a", "points": [780, 297, 800, 297, 800, 343, 780, 343]}, {"ignore": 0, "transcription": "1", "points": [801, 297, 837, 297, 837, 342, 801, 342]}, {"ignore": 0, "transcription": "7", "points": [832, 294, 867, 294, 867, 341, 832, 341]}, {"ignore": 0, "transcription": "7", "points": [869, 295, 903, 295, 903, 342, 869, 342]}, {"ignore": 0, "transcription": "3", "points": [903, 294, 936, 294, 936, 341, 903, 341]}, {"ignore": 0, "transcription": "9", "points": [936, 294, 971, 294, 971, 342, 936, 342]}, {"ignore": 0, "transcription": "7", "points": [970, 293, 1004, 293, 1004, 340, 970, 340]}, {"ignore": 0, "transcription": "9", "points": [1004, 294, 1039, 294, 1039, 340, 1004, 340]}, {"ignore": 0, "transcription": "8", "points": [1036, 291, 1074, 291, 1074, 340, 1036, 340]}, {"ignore": 0, "transcription": "8", "points": [1074, 292, 1107, 292, 1107, 339, 1074, 339]}, {"ignore": 0, "transcription": "9", "points": [1105, 292, 1138, 292, 1138, 337, 1105, 337]}, {"ignore": 0, "transcription": "3", "points": [1142, 292, 1174, 292, 1174, 337, 1142, 337]}, {"ignore": 0, "transcription": "\u90d1", "points": [1218, 288, 1278, 288, 1278, 339, 1218, 339]}, {"ignore": 0, "transcription": "\u5dde", "points": [1274, 287, 1332, 287, 1332, 339, 1274, 339]}, {"ignore": 0, "transcription": "\u603b", "points": [1332, 287, 1386, 287, 1386, 336, 1332, 336]}, {"ignore": 0, "transcription": "\u5e97", "points": [1386, 287, 1441, 287, 1441, 336, 1386, 336]}, {"ignore": 0, "transcription": "\u96ea", "points": [1624, 186, 1681, 186, 1681, 239, 1624, 239]}, {"ignore": 0, "transcription": "\u82b1", "points": [1680, 184, 1740, 184, 1740, 235, 1680, 235]}, {"ignore": 0, "transcription": "\u52c7", "points": [1595, 239, 1643, 239, 1643, 297, 1595, 297]}, {"ignore": 0, "transcription": "\u95ef", "points": [1641, 244, 1691, 244, 1691, 287, 1641, 287]}, {"ignore": 0, "transcription": "\u5929", "points": [1677, 239, 1737, 239, 1737, 298, 1677, 298]}, {"ignore": 0, "transcription": "\u6daf", "points": [1726, 236, 1784, 236, 1784, 287, 1726, 287]}, {"ignore": 0, "transcription": "\u5e72", "points": [900, 490, 930, 490, 930, 542, 900, 542]}, {"ignore": 0, "transcription": "\u9505", "points": [928, 487, 983, 487, 983, 538, 928, 538]}, {"ignore": 0, "transcription": "\u867e", "points": [979, 487, 1037, 487, 1037, 540, 979, 540]}, {"ignore": 0, "transcription": "\uff0c", "points": [1033, 496, 1052, 496, 1052, 541, 1033, 541]}, {"ignore": 0, "transcription": "\u5403", "points": [1084, 482, 1141, 482, 1141, 535, 1084, 535]}, {"ignore": 0, "transcription": "\u4e00", "points": [1133, 488, 1187, 488, 1187, 518, 1133, 518]}, {"ignore": 0, "transcription": "\u9001", "points": [1187, 479, 1243, 479, 1243, 532, 1187, 532]}, {"ignore": 0, "transcription": "\u4e00", "points": [1239, 484, 1291, 484, 1291, 512, 1239, 512]}, {"ignore": 0, "transcription": "\uff0c", "points": [1292, 488, 1310, 488, 1310, 533, 1292, 533]}, {"ignore": 0, "transcription": "\u9c7c", "points": [1336, 472, 1378, 472, 1378, 524, 1336, 524]}], "lines": [{"ignore": 0, "transcription": "\u805a\u767e", "points": [408, 106, 465, 106, 465, 222, 408, 222]}, {"ignore": 0, "transcription": "\u8766\u5175\u87f9\u7172", "points": [551, 94, 1435, 91, 1435, 249, 551, 257]}, {"ignore": 0, "transcription": "\u8fd9\u662f\u53ef\u4ee5\u5148\u5403", "points": [186, 260, 466, 260, 466, 303, 186, 303]}, {"ignore": 0, "transcription": "\u540e\u6dae\u7684\u5e72\u9505\u83dc", "points": [221, 314, 492, 310, 492, 352, 221, 355]}, {"ignore": 0, "transcription": "\u52a0\u76df\u7535\u8bdd\uff1a", "points": [547, 293, 799, 293, 799, 347, 547, 347]}, {"ignore": 0, "transcription": "17739798893", "points": [801, 296, 1175, 291, 1175, 337, 801, 342]}, {"ignore": 0, "transcription": "\u90d1\u5dde\u603b\u5e97", "points": [1221, 286, 1441, 286, 1441, 338, 1221, 338]}, {"ignore": 0, "transcription": "\u96ea\u82b1", "points": [1620, 183, 1731, 183, 1744, 237, 1632, 237]}, {"ignore": 0, "transcription": "\u52c7\u95ef\u5929\u6daf", "points": [1596, 237, 1787, 237, 1780, 296, 1592, 296]}, {"ignore": 0, "transcription": "\u5e72\u9505\u867e\uff0c\u5403\u4e00\u9001\u4e00\uff0c\u9c7c", "points": [902, 487, 1382, 472, 1382, 524, 902, 541]}]}
